[{"UserName": "@@000af40bf2aa9421c398027af971f9d3f0d2f98ec1b30a34a0592016aaa40f5b", "City": "", "DisplayName": "", "UniFriend": 0, "MemberList": [], "PYQuanPin": "quyanglushaokaoxiaofendui", "RemarkPYInitial": "", "Sex": 0, "AppAccountFlag": 0, "VerifyFlag": 0, "Province": "", "KeyWord": "", "RemarkName": "", "PYInitial": "QYLSKXFD", "IsOwner": 0, "ChatRoomId": 0, "HideInputBarFlag": 0, "EncryChatRoomId": "", "AttrStatus": 0, "SnsFlag": 0, "MemberCount": 0, "OwnerUin": 0, "Alias": "", "Signature": "", "ContactFlag": 3, "NickName": "\u66f2\u9633\u8def\u70e7\u70e4\u5c0f\u5206\u961f", "RemarkPYQuanPin": "", "HeadImgUrl": "/cgi-bin/mmwebwx-bin/webwxgetheadimg?seq=622091679&username=@@000af40bf2aa9421c398027af971f9d3f0d2f98ec1b30a34a0592016aaa40f5b&skey=@crypt_8d61424b_1262abc3e43d1987720e2c8c2a8d1a03", "Uin": 0, "StarFriend": 0, "Statues": 1}, {"UserName": "@@885d42c048524535d0bb4b3f6ee9513eb29a59a7a8e93e47281b3ac51791a9c1", "City": "", "DisplayName": "", "UniFriend": 0, "MemberList": [], "PYQuanPin": "huangpuouyumaoqiuxiaofendui", "RemarkPYInitial": "", "Sex": 0, "AppAccountFlag": 0, "VerifyFlag": 0, "Province": "", "KeyWord": "", "RemarkName": "", "PYInitial": "HPOYMQXFD", "IsOwner": 1, "ChatRoomId": 0, "HideInputBarFlag": 0, "EncryChatRoomId": "", "AttrStatus": 0, "SnsFlag": 0, "MemberCount": 0, "OwnerUin": 0, "Alias": "", "Signature": "", "ContactFlag": 3, "NickName": "\u9ec4\u6d66\u533a\u7fbd\u6bdb\u7403\u5c0f\u5206\u961f", "RemarkPYQuanPin": "", "HeadImgUrl": "/cgi-bin/mmwebwx-bin/webwxgetheadimg?seq=622121128&username=@@885d42c048524535d0bb4b3f6ee9513eb29a59a7a8e93e47281b3ac51791a9c1&skey=@crypt_8d61424b_1262abc3e43d1987720e2c8c2a8d1a03", "Uin": 0, "StarFriend": 0, "Statues": 1}, {"UserName": "@@a8e0f21b0be91409e9de7b30a5c18be15821a27c8979a431f3f473d3b1d52188", "City": "", "DisplayName": "", "UniFriend": 0, "MemberList": [], "PYQuanPin": "xinzhuantixiaozu", "RemarkPYInitial": "", "Sex": 0, "AppAccountFlag": 0, "VerifyFlag": 0, "Province": "", "KeyWord": "", "RemarkName": "", "PYInitial": "XZTXZ", "IsOwner": 1, "ChatRoomId": 0, "HideInputBarFlag": 0, "EncryChatRoomId": "", "AttrStatus": 0, "SnsFlag": 0, "MemberCount": 0, "OwnerUin": 0, "Alias": "", "Signature": "", "ContactFlag": 3, "NickName": "\u65b0\u4e13\u9898\u5c0f\u7ec4", "RemarkPYQuanPin": "", "HeadImgUrl": "/cgi-bin/mmwebwx-bin/webwxgetheadimg?seq=628496214&username=@@a8e0f21b0be91409e9de7b30a5c18be15821a27c8979a431f3f473d3b1d52188&skey=@crypt_8d61424b_1262abc3e43d1987720e2c8c2a8d1a03", "Uin": 0, "StarFriend": 0, "Statues": 1}, {"UserName": "@@934c9da4d5b01f47b51cfa438a98cf54bed155d6e1445437a8acc5f4bd649fab", "City": "", "DisplayName": "", "UniFriend": 0, "MemberList": [], "PYQuanPin": "gongchuangmeihaojiayuanPRO", "RemarkPYInitial": "", "Sex": 0, "AppAccountFlag": 0, "VerifyFlag": 0, "Province": "", "KeyWord": "", "RemarkName": "", "PYInitial": "GCMHJYPRO", "IsOwner": 1, "ChatRoomId": 0, "HideInputBarFlag": 0, "EncryChatRoomId": "", "AttrStatus": 0, "SnsFlag": 0, "MemberCount": 0, "OwnerUin": 0, "Alias": "", "Signature": "", "ContactFlag": 1, "NickName": "\u5171\u521b\u7f8e\u597d\u5bb6\u56edPRO", "RemarkPYQuanPin": "", "HeadImgUrl": "/cgi-bin/mmwebwx-bin/webwxgetheadimg?seq=643423070&username=@@934c9da4d5b01f47b51cfa438a98cf54bed155d6e1445437a8acc5f4bd649fab&skey=@crypt_8d61424b_1262abc3e43d1987720e2c8c2a8d1a03", "Uin": 0, "StarFriend": 0, "Statues": 1}, {"UserName": "@@8b44ab8ab294fb10d81c95e54dcc62f921a82590ac7fca55e9a36731a25e4870", "City": "", "DisplayName": "", "UniFriend": 0, "MemberList": [], "PYQuanPin": "fengyiyangdechengzi", "RemarkPYInitial": "", "Sex": 0, "AppAccountFlag": 0, "VerifyFlag": 0, "Province": "", "KeyWord": "", "RemarkName": "", "PYInitial": "FYYDCZ", "IsOwner": 1, "ChatRoomId": 0, "HideInputBarFlag": 0, "EncryChatRoomId": "", "AttrStatus": 0, "SnsFlag": 0, "MemberCount": 0, "OwnerUin": 0, "Alias": "", "Signature": "", "ContactFlag": 3, "NickName": "\u98ce\u4e00\u6837\u7684\u6a59\u5b50", "RemarkPYQuanPin": "", "HeadImgUrl": "/cgi-bin/mmwebwx-bin/webwxgetheadimg?seq=654306075&username=@@8b44ab8ab294fb10d81c95e54dcc62f921a82590ac7fca55e9a36731a25e4870&skey=@crypt_8d61424b_1262abc3e43d1987720e2c8c2a8d1a03", "Uin": 0, "StarFriend": 0, "Statues": 0}, {"UserName": "@@dd3c2a33d056c2b34a6096b25059e6fb712fb8d030a23c6dc7da4ef35a595375", "City": "", "DisplayName": "", "UniFriend": 0, "MemberList": [], "PYQuanPin": "heiyufeiyang", "RemarkPYInitial": "", "Sex": 0, "AppAccountFlag": 0, "VerifyFlag": 0, "Province": "", "KeyWord": "", "RemarkName": "", "PYInitial": "HYFY", "IsOwner": 1, "ChatRoomId": 0, "HideInputBarFlag": 0, "EncryChatRoomId": "", "AttrStatus": 0, "SnsFlag": 0, "MemberCount": 0, "OwnerUin": 0, "Alias": "", "Signature": "", "ContactFlag": 3, "NickName": "\u9ed1\u7fbd\u98de\u626c", "RemarkPYQuanPin": "", "HeadImgUrl": "/cgi-bin/mmwebwx-bin/webwxgetheadimg?seq=668453191&username=@@dd3c2a33d056c2b34a6096b25059e6fb712fb8d030a23c6dc7da4ef35a595375&skey=@crypt_8d61424b_1262abc3e43d1987720e2c8c2a8d1a03", "Uin": 0, "StarFriend": 0, "Statues": 1}, {"UserName": "@@bc3af5cb5b4b7989f6044d70bdd448350198c78ccdb6c36ac631a8ac39da02a7", "City": "", "DisplayName": "", "UniFriend": 0, "MemberList": [], "PYQuanPin": "weixinxiaochengxuceshiqun", "RemarkPYInitial": "", "Sex": 0, "AppAccountFlag": 0, "VerifyFlag": 0, "Province": "", "KeyWord": "", "RemarkName": "", "PYInitial": "WXXCXCSQ", "IsOwner": 1, "ChatRoomId": 0, "HideInputBarFlag": 0, "EncryChatRoomId": "", "AttrStatus": 0, "SnsFlag": 0, "MemberCount": 0, "OwnerUin": 0, "Alias": "", "Signature": "", "ContactFlag": 3, "NickName": "\u5fae\u4fe1\u5c0f\u7a0b\u5e8f\u6d4b\u8bd5\u7fa4", "RemarkPYQuanPin": "", "HeadImgUrl": "/cgi-bin/mmwebwx-bin/webwxgetheadimg?seq=670970864&username=@@bc3af5cb5b4b7989f6044d70bdd448350198c78ccdb6c36ac631a8ac39da02a7&skey=@crypt_8d61424b_1262abc3e43d1987720e2c8c2a8d1a03", "Uin": 0, "StarFriend": 0, "Statues": 1}, {"UserName": "@@591b90c8a69ba55a933673c91dc29f1376179d32ff0b8f9c44de2c7ae7656f2c", "City": "", "DisplayName": "", "UniFriend": 0, "MemberList": [], "PYQuanPin": "yuqiutongjidaxueshanghaiwaiguoyu", "RemarkPYInitial": "", "Sex": 0, "AppAccountFlag": 0, "VerifyFlag": 0, "Province": "", "KeyWord": "", "RemarkName": "", "PYInitial": "YQTJDXSHWGY", "IsOwner": 1, "ChatRoomId": 0, "HideInputBarFlag": 0, "EncryChatRoomId": "", "AttrStatus": 0, "SnsFlag": 0, "MemberCount": 0, "OwnerUin": 0, "Alias": "", "Signature": "", "ContactFlag": 3, "NickName": "\u7fbd\u7403@\u540c\u6d4e\u5927\u5b66@\u4e0a\u6d77\u5916\u56fd\u8bed", "RemarkPYQuanPin": "", "HeadImgUrl": "/cgi-bin/mmwebwx-bin/webwxgetheadimg?seq=670983906&username=@@591b90c8a69ba55a933673c91dc29f1376179d32ff0b8f9c44de2c7ae7656f2c&skey=@crypt_8d61424b_1262abc3e43d1987720e2c8c2a8d1a03", "Uin": 0, "StarFriend": 0, "Statues": 1}, {"UserName": "@@1df92e135c28ded5620a63e0c8b9862964d07a723d870f856ea5e2bff8008027", "City": "", "DisplayName": "", "UniFriend": 0, "MemberList": [], "PYQuanPin": "chenqiezuobudao", "RemarkPYInitial": "", "Sex": 0, "AppAccountFlag": 0, "VerifyFlag": 0, "Province": "", "KeyWord": "", "RemarkName": "", "PYInitial": "CQZBD", "IsOwner": 1, "ChatRoomId": 0, "HideInputBarFlag": 0, "EncryChatRoomId": "", "AttrStatus": 0, "SnsFlag": 0, "MemberCount": 0, "OwnerUin": 0, "Alias": "", "Signature": "", "ContactFlag": 3, "NickName": "\u81e3\u59be\u5750\u4e0d\u5230", "RemarkPYQuanPin": "", "HeadImgUrl": "/cgi-bin/mmwebwx-bin/webwxgetheadimg?seq=671058805&username=@@1df92e135c28ded5620a63e0c8b9862964d07a723d870f856ea5e2bff8008027&skey=@crypt_8d61424b_1262abc3e43d1987720e2c8c2a8d1a03", "Uin": 0, "StarFriend": 0, "Statues": 1}, {"UserName": "@@af3b06b3ea562a7f24aa73ec25ce659d66a53c3e85cc15d60baf132aac7cb754", "City": "", "DisplayName": "", "UniFriend": 0, "MemberList": [], "PYQuanPin": "songfurenzhijia", "RemarkPYInitial": "", "Sex": 0, "AppAccountFlag": 0, "VerifyFlag": 0, "Province": "", "KeyWord": "", "RemarkName": "", "PYInitial": "SFRZJ", "IsOwner": 1, "ChatRoomId": 0, "HideInputBarFlag": 0, "EncryChatRoomId": "", "AttrStatus": 0, "SnsFlag": 0, "MemberCount": 0, "OwnerUin": 0, "Alias": "", "Signature": "", "ContactFlag": 3, "NickName": "\u5b8b\u592b\u4eba\u4e4b\u5bb6", "RemarkPYQuanPin": "", "HeadImgUrl": "/cgi-bin/mmwebwx-bin/webwxgetheadimg?seq=646413058&username=@@af3b06b3ea562a7f24aa73ec25ce659d66a53c3e85cc15d60baf132aac7cb754&skey=@crypt_8d61424b_1262abc3e43d1987720e2c8c2a8d1a03", "Uin": 0, "StarFriend": 0, "Statues": 1}, {"UserName": "@@f149deaec66c7a706f6a4255b696f011a06f34a25045cc0afb2713a6d7285b92", "City": "", "DisplayName": "", "UniFriend": 0, "MemberList": [], "PYQuanPin": "guaneryixiao", "RemarkPYInitial": "", "Sex": 0, "AppAccountFlag": 0, "VerifyFlag": 0, "Province": "", "KeyWord": "", "RemarkName": "", "PYInitial": "GEYX", "IsOwner": 0, "ChatRoomId": 0, "HideInputBarFlag": 0, "EncryChatRoomId": "", "AttrStatus": 0, "SnsFlag": 0, "MemberCount": 0, "OwnerUin": 0, "Alias": "", "Signature": "", "ContactFlag": 3, "NickName": "\u839e\u5c14\u4e00\u7b11", "RemarkPYQuanPin": "", "HeadImgUrl": "/cgi-bin/mmwebwx-bin/webwxgetheadimg?seq=671067307&username=@@f149deaec66c7a706f6a4255b696f011a06f34a25045cc0afb2713a6d7285b92&skey=@crypt_8d61424b_1262abc3e43d1987720e2c8c2a8d1a03", "Uin": 0, "StarFriend": 0, "Statues": 0}, {"UserName": "@@50e2dfd55b3d4030c05e8e40e904fbc6580115afb739adc8e73225c55d17336c", "City": "", "DisplayName": "", "UniFriend": 0, "MemberList": [], "PYQuanPin": "haoyunmamijiaoliuqun", "RemarkPYInitial": "", "Sex": 0, "AppAccountFlag": 0, "VerifyFlag": 0, "Province": "", "KeyWord": "", "RemarkName": "", "PYInitial": "HYMMJLQ", "IsOwner": 0, "ChatRoomId": 0, "HideInputBarFlag": 0, "EncryChatRoomId": "", "AttrStatus": 0, "SnsFlag": 0, "MemberCount": 0, "OwnerUin": 0, "Alias": "", "Signature": "", "ContactFlag": 3, "NickName": "\u597d\u5b55\u5988\u54aa\u4ea4\u6d41\u7fa4", "RemarkPYQuanPin": "", "HeadImgUrl": "/cgi-bin/mmwebwx-bin/webwxgetheadimg?seq=671109170&username=@@50e2dfd55b3d4030c05e8e40e904fbc6580115afb739adc8e73225c55d17336c&skey=@crypt_8d61424b_1262abc3e43d1987720e2c8c2a8d1a03", "Uin": 0, "StarFriend": 0, "Statues": 0}, {"UserName": "@@fb504cc64314a66f940e346280f8964cd8aa83f1cfa6aa52fb1c73ef8ed071a2", "City": "", "DisplayName": "", "UniFriend": 0, "MemberList": [], "PYQuanPin": "TOCyanfazu", "RemarkPYInitial": "", "Sex": 0, "AppAccountFlag": 0, "VerifyFlag": 0, "Province": "", "KeyWord": "", "RemarkName": "", "PYInitial": "TOCYFZ", "IsOwner": 0, "ChatRoomId": 0, "HideInputBarFlag": 0, "EncryChatRoomId": "", "AttrStatus": 0, "SnsFlag": 0, "MemberCount": 0, "OwnerUin": 0, "Alias": "", "Signature": "", "ContactFlag": 3, "NickName": "TOC\u7814\u53d1\u7ec4", "RemarkPYQuanPin": "", "HeadImgUrl": "/cgi-bin/mmwebwx-bin/webwxgetheadimg?seq=671079248&username=@@fb504cc64314a66f940e346280f8964cd8aa83f1cfa6aa52fb1c73ef8ed071a2&skey=@crypt_8d61424b_1262abc3e43d1987720e2c8c2a8d1a03", "Uin": 0, "StarFriend": 0, "Statues": 0}, {"UserName": "@@adf5f2dc69830f31e6ec5693c95569a2a18381b4448f7820d8b64d857c1795ef", "City": "", "DisplayName": "", "UniFriend": 0, "MemberList": [], "PYQuanPin": "tongjiyumaoqiubiubiubiu", "RemarkPYInitial": "", "Sex": 0, "AppAccountFlag": 0, "VerifyFlag": 0, "Province": "", "KeyWord": "", "RemarkName": "", "PYInitial": "TJYMQBIUBIUBIU", "IsOwner": 0, "ChatRoomId": 0, "HideInputBarFlag": 0, "EncryChatRoomId": "", "AttrStatus": 0, "SnsFlag": 0, "MemberCount": 0, "OwnerUin": 0, "Alias": "", "Signature": "", "ContactFlag": 3, "NickName": "\u540c\u6d4e\u7fbd\u6bdb\u7403biubiubiu~", "RemarkPYQuanPin": "", "HeadImgUrl": "/cgi-bin/mmwebwx-bin/webwxgetheadimg?seq=671135326&username=@@adf5f2dc69830f31e6ec5693c95569a2a18381b4448f7820d8b64d857c1795ef&skey=@crypt_8d61424b_1262abc3e43d1987720e2c8c2a8d1a03", "Uin": 0, "StarFriend": 0, "Statues": 0}, {"UserName": "@@19fd163f9d9e49c9c74af9416176ec990881bbc2e042853d6d78b0e41d6b1037", "City": "", "DisplayName": "", "UniFriend": 0, "MemberList": [], "PYQuanPin": "jiqirenceshiqun", "RemarkPYInitial": "", "Sex": 0, "AppAccountFlag": 0, "VerifyFlag": 0, "Province": "", "KeyWord": "", "RemarkName": "", "PYInitial": "JQRCSQ", "IsOwner": 1, "ChatRoomId": 0, "HideInputBarFlag": 0, "EncryChatRoomId": "", "AttrStatus": 0, "SnsFlag": 0, "MemberCount": 0, "OwnerUin": 0, "Alias": "", "Signature": "", "ContactFlag": 3, "NickName": "\u673a\u5668\u4eba\u6d4b\u8bd5\u7fa4", "RemarkPYQuanPin": "", "HeadImgUrl": "/cgi-bin/mmwebwx-bin/webwxgetheadimg?seq=671153147&username=@@19fd163f9d9e49c9c74af9416176ec990881bbc2e042853d6d78b0e41d6b1037&skey=@crypt_8d61424b_1262abc3e43d1987720e2c8c2a8d1a03", "Uin": 0, "StarFriend": 0, "Statues": 1}]